setup.cfg
setup.py
MAD.egg-info/PKG-INFO
MAD.egg-info/SOURCES.txt
MAD.egg-info/dependency_links.txt
MAD.egg-info/top_level.txt
mad/__init__.py
mad/__main__.py
mad/environment.py
mad/evaluation.py
mad/log.py
mad/monitoring.py
mad/parsetab.py
mad/parsing.py
mad/scheduling.py
mad/storage.py
mad/ui.py
mad/ast/__init__.py
mad/ast/actions.py
mad/ast/commons.py
mad/ast/definitions.py
mad/ast/settings.py
mad/simulation/__init__.py
mad/simulation/autoscaling.py
mad/simulation/backoff.py
mad/simulation/client.py
mad/simulation/commons.py
mad/simulation/events.py
mad/simulation/factory.py
mad/simulation/monitoring.py
mad/simulation/requests.py
mad/simulation/service.py
mad/simulation/tasks.py
mad/simulation/throttling.py
mad/simulation/workers.py
mad/utils/__init__.py
mad/utils/releasing.py
mad/validation/__init__.py
mad/validation/engine.py
mad/validation/issues.py
tests/__init__.py
tests/fakes.py
tests/test_acceptance.py
tests/test_environment.py
tests/test_evaluation.py
tests/test_interpreter.py
tests/test_log.py
tests/test_main.py
tests/test_monitoring.py
tests/test_parser.py
tests/test_scheduling.py
tests/test_ui.py
tests/test_validation.py
tests/ast/__init__.py
tests/ast/test_ast.py
tests/ast/test_settings.py
tests/simulation/__init__.py
tests/simulation/test_autoscaling.py
tests/simulation/test_backoff.py
tests/simulation/test_events.py
tests/simulation/test_monitoring.py
tests/simulation/test_tasks.py
tests/simulation/test_throttling.py
tests/simulation/test_workers.py
tests/utils/__init__.py
tests/utils/test_releasing.py