Metadata-Version: 1.1
Name: MAD
Version: 0.2.0
Summary: Simulation of microservices architectures dynamics
Home-page: https://github.com/fchauvel/MAD
Author: Franck Chauvel
Author-email: franck.chauvel@gmail.com
License: GPLv3
Download-URL: https://github.com/fchauvel/mad/tarball/v0.1.1
Platform: UNKNOWN
Classifier: Development Status :: 3 - Alpha
Classifier: Intended Audience :: Science/Research
Classifier: Environment :: Console
Classifier: License :: OSI Approved :: GNU General Public License v3 or later (GPLv3+)
Classifier: Natural Language :: English
Classifier: Programming Language :: Python :: 3.4
Classifier: Topic :: Scientific/Engineering
Classifier: Topic :: Software Development :: Quality Assurance
